{
  "type": "confused_words",
  "name": "Yazımı Karıştırılan Kelimeler",
  "description": "Türkçe'de sıklıkla yanlış yazılan ve birbirine karıştırılan kelimelerin doğru yazılışları",
  "categories": [
    {
      "letter": "A",
      "words": [
        {
          "wrong": ["ataşe"],
          "correct": "ateşe",
          "meaning": "elçilik uzmanı"
        },
        {
          "wrong": ["amblem"],
          "correct": "ablem",
          "meaning": null
        },
        {
          "wrong": ["acaip"],
          "correct": "acayip",
          "meaning": null
        },
        {
          "wrong": ["acenta"],
          "correct": "acente",
          "meaning": null
        },
        {
          "wrong": ["aut"],
          "correct": "avut",
          "meaning": "dış"
        },
        {
          "wrong": ["Azerbeycan"],
          "correct": "Azerbaycan",
          "meaning": null
        },
        {
          "wrong": ["acitasyon"],
          "correct": "ajitasyon",
          "meaning": "kışkırtma, duygu sömürüsü yapma"
        },
        {
          "wrong": ["adele"],
          "correct": "adale",
          "meaning": null
        },
        {
          "wrong": ["afaroz"],
          "correct": "aforoz",
          "meaning": "Hristiyanlıkta cemaatten kovma cezası, darılıp biriyle konuşmama, uzaklaştırma"
        },
        {
          "wrong": ["afilli"],
          "correct": "afili",
          "meaning": "gösterişli, çalımlı"
        },
        {
          "wrong": ["ahçı"],
          "correct": "aşçı",
          "meaning": null
        },
        {
          "wrong": ["ahpap"],
          "correct": "ahbap",
          "meaning": null
        },
        {
          "wrong": ["akapunktur"],
          "correct": "akupunktur",
          "meaning": "iğne batırılarak yapılan tedavi"
        },
        {
          "wrong": ["alarım"],
          "correct": "alarm",
          "meaning": null
        },
        {
          "wrong": ["aliminyum", "alimünyum"],
          "correct": "alüminyum",
          "meaning": null
        },
        {
          "wrong": ["allerji"],
          "correct": "alerji",
          "meaning": null
        },
        {
          "wrong": ["alobora"],
          "correct": "alabora",
          "meaning": "geminin yan yatması"
        },
        {
          "wrong": ["amartisör"],
          "correct": "amortisör",
          "meaning": null
        },
        {
          "wrong": ["anfi"],
          "correct": "amfi",
          "meaning": "basamaklı olarak yükselen büyük derslik"
        },
        {
          "wrong": ["anotomi"],
          "correct": "anatomi",
          "meaning": null
        },
        {
          "wrong": ["antiparantez"],
          "correct": "antrparantez",
          "meaning": null
        },
        {
          "wrong": ["antreman"],
          "correct": "antrenman",
          "meaning": null
        },
        {
          "wrong": ["aparatif", "aperatif"],
          "correct": "aperitif",
          "meaning": "ön içki"
        },
        {
          "wrong": ["aporlor", "hoporlër", "opörler"],
          "correct": "hoparlör",
          "meaning": null
        },
        {
          "wrong": ["aptes"],
          "correct": "abdest",
          "meaning": null
        },
        {
          "wrong": ["arabeks"],
          "correct": "arabesk",
          "meaning": null
        },
        {
          "wrong": ["arefe"],
          "correct": "arife",
          "meaning": null
        },
        {
          "wrong": ["arozöz"],
          "correct": "arazöz",
          "meaning": "yolları ve yol kenarlarındaki yeşillikleri sulamakta kullanılan araç"
        },
        {
          "wrong": ["artiz", "artis"],
          "correct": "artist",
          "meaning": null
        },
        {
          "wrong": ["askari"],
          "correct": "asgari",
          "meaning": "en az, en düşük"
        },
        {
          "wrong": ["assubay"],
          "correct": "astsubay",
          "meaning": null
        },
        {
          "wrong": ["asvalt"],
          "correct": "asfalt",
          "meaning": null
        },
        {
          "wrong": ["aşentiyon", "aşantiyon"],
          "correct": "eşantiyon",
          "meaning": null
        },
        {
          "wrong": ["aşofman", "eşortman"],
          "correct": "eşofman",
          "meaning": null
        },
        {
          "wrong": ["ataç"],
          "correct": "ataş",
          "meaning": "tutturgaç"
        },
        {
          "wrong": ["atelye"],
          "correct": "atölye",
          "meaning": null
        }
      ]
    },
    {
      "letter": "B",
      "words": [
        {
          "wrong": ["barsak"],
          "correct": "bağırsak",
          "meaning": null
        },
        {
          "wrong": ["bilader"],
          "correct": "birader",
          "meaning": null
        },
        {
          "wrong": ["bilimum"],
          "correct": "bilumum",
          "meaning": null
        },
        {
          "wrong": ["birfiil"],
          "correct": "bilfiil",
          "meaning": null
        },
        {
          "wrong": ["birhaber"],
          "correct": "bihaber",
          "meaning": null
        },
        {
          "wrong": ["boğa yılanı"],
          "correct": "boa yılanı",
          "meaning": null
        },
        {
          "wrong": ["boy pos"],
          "correct": "boy bos",
          "meaning": null
        },
        {
          "wrong": ["boğça", "poaça", "poça"],
          "correct": "poğaça",
          "meaning": null
        },
        {
          "wrong": ["büsküüt", "püsküüt", "pisküüt", "pisküvi", "püsküvüt"],
          "correct": "bisküvi",
          "meaning": null
        }
      ]
    },
    {
      "letter": "C",
      "words": [
        {
          "wrong": ["canbaz"],
          "correct": "cambaz",
          "meaning": null
        },
        {
          "wrong": ["candarma", "cenderme"],
          "correct": "jandarma",
          "meaning": null
        },
        {
          "wrong": ["celatin"],
          "correct": "jelatin",
          "meaning": null
        },
        {
          "wrong": ["ceryan"],
          "correct": "cereyan",
          "meaning": null
        },
        {
          "wrong": ["ceton"],
          "correct": "jeton",
          "meaning": null
        },
        {
          "wrong": ["cimnastik"],
          "correct": "jimnastik",
          "meaning": null
        },
        {
          "wrong": ["ciyer"],
          "correct": "ciğer",
          "meaning": null
        },
        {
          "wrong": ["civa"],
          "correct": "cıva",
          "meaning": null
        }
      ]
    },
    {
      "letter": "Ç",
      "words": [
        {
          "wrong": ["çekinser"],
          "correct": "çekimser",
          "meaning": null
        },
        {
          "wrong": ["çiflik"],
          "correct": "çiftlik",
          "meaning": null
        },
        {
          "wrong": ["çinakop"],
          "correct": "çinekop",
          "meaning": null
        },
        {
          "wrong": ["çukulata", "çukolata"],
          "correct": "çikolata",
          "meaning": null
        }
      ]
    },
    {
      "letter": "D",
      "words": [
        {
          "wrong": ["dekarasyon"],
          "correct": "dekorasyon",
          "meaning": null
        },
        {
          "wrong": ["dekaratör"],
          "correct": "dekoratör",
          "meaning": null
        },
        {
          "wrong": ["dersane"],
          "correct": "dershane",
          "meaning": null
        },
        {
          "wrong": ["dinazor"],
          "correct": "dinozor",
          "meaning": null
        },
        {
          "wrong": ["direk"],
          "correct": "direkt",
          "meaning": null
        },
        {
          "wrong": ["döğmek"],
          "correct": "dövmek",
          "meaning": null
        },
        {
          "wrong": ["döküman"],
          "correct": "doküman",
          "meaning": "belge"
        },
        {
          "wrong": ["dökümanter"],
          "correct": "dokümanter",
          "meaning": "belgesel"
        }
      ]
    },
    {
      "letter": "E",
      "words": [
        {
          "wrong": ["egzantrik", "ekzantrik", "egsantrik"],
          "correct": "eksantrik",
          "meaning": "dış merkezli, ayrıksı"
        },
        {
          "wrong": ["egzos", "egsoz", "eksoz", "egzost", "eksozt"],
          "correct": "egzoz",
          "meaning": null
        },
        {
          "wrong": ["ensitü"],
          "correct": "enstitü",
          "meaning": null
        },
        {
          "wrong": ["entellektüel"],
          "correct": "entelektüel",
          "meaning": null
        },
        {
          "wrong": ["entrasan"],
          "correct": "enteresan",
          "meaning": null
        },
        {
          "wrong": ["erezyon"],
          "correct": "erozyon",
          "meaning": "aşınma"
        },
        {
          "wrong": ["eskirim"],
          "correct": "eskrim",
          "meaning": null
        },
        {
          "wrong": ["espiri"],
          "correct": "espri",
          "meaning": null
        },
        {
          "wrong": ["eşgal", "eşkal"],
          "correct": "eşkâl",
          "meaning": "dıştan görünüş, biçim"
        },
        {
          "wrong": ["evsane"],
          "correct": "efsane",
          "meaning": null
        },
        {
          "wrong": ["ezzane"],
          "correct": "eczane",
          "meaning": null
        }
      ]
    },
    {
      "letter": "F",
      "words": [
        {
          "wrong": ["faliyet"],
          "correct": "faaliyet",
          "meaning": null
        },
        {
          "wrong": ["fantazi"],
          "correct": "fantezi",
          "meaning": "değişik heves, değişik beğeni"
        },
        {
          "wrong": ["fasülye"],
          "correct": "fasulye",
          "meaning": null
        },
        {
          "wrong": ["fermar"],
          "correct": "fermuar",
          "meaning": null
        },
        {
          "wrong": ["fesetmek"],
          "correct": "feshetmek",
          "meaning": "bozmak, dağıtmak"
        },
        {
          "wrong": ["fiat"],
          "correct": "fiyat",
          "meaning": null
        },
        {
          "wrong": ["filim"],
          "correct": "film",
          "meaning": null
        },
        {
          "wrong": ["fites"],
          "correct": "vites",
          "meaning": null
        },
        {
          "wrong": ["florasan"],
          "correct": "floresan",
          "meaning": null
        }
      ]
    },
    {
      "letter": "G",
      "words": [
        {
          "wrong": ["gangaster"],
          "correct": "gangster",
          "meaning": null
        },
        {
          "wrong": ["gangren"],
          "correct": "kangren",
          "meaning": null
        },
        {
          "wrong": ["gardolap"],
          "correct": "gardırop",
          "meaning": null
        },
        {
          "wrong": ["gaste", "gazte"],
          "correct": "gazete",
          "meaning": null
        },
        {
          "wrong": ["gravat"],
          "correct": "kravat",
          "meaning": null
        }
      ]
    },
    {
      "letter": "H",
      "words": [
        {
          "wrong": ["halel"],
          "correct": "helâl",
          "meaning": "dinin kurallarına aykırı olmayan, dinî bakımdan yasaklanmamış olan, haram karşıtı",
          "note": "halel: bozma, bozukluk anlamına gelir"
        },
        {
          "wrong": ["hakkaten"],
          "correct": "hakikaten",
          "meaning": null
        },
        {
          "wrong": ["halisinasyon", "halisünasyon"],
          "correct": "halüsinasyon",
          "meaning": "sanrı"
        },
        {
          "wrong": ["haremlik selamlık"],
          "correct": "harem selamlık",
          "meaning": null
        },
        {
          "wrong": ["harfiyat"],
          "correct": "hafriyat",
          "meaning": "kazı"
        },
        {
          "wrong": ["herkez", "herkeş"],
          "correct": "herkes",
          "meaning": null
        },
        {
          "wrong": ["heycan"],
          "correct": "heyecan",
          "meaning": null
        },
        {
          "wrong": ["Hıristiyan"],
          "correct": "Hristiyan",
          "meaning": null
        }
      ]
    },
    {
      "letter": "I",
      "words": [
        {
          "wrong": ["ıskonto"],
          "correct": "iskonto",
          "meaning": null
        },
        {
          "wrong": ["ıstırap"],
          "correct": "ızdırap",
          "meaning": null
        }
      ]
    },
    {
      "letter": "İ",
      "words": [
        {
          "wrong": ["Istanbul", "İstambul"],
          "correct": "İstanbul",
          "meaning": null
        },
        {
          "wrong": ["istakoz"],
          "correct": "ıstakoz",
          "meaning": null
        },
        {
          "wrong": ["ilizyon", "ilüzyon"],
          "correct": "illüzyon",
          "meaning": "yanılsama"
        },
        {
          "wrong": ["inkilap"],
          "correct": "inkılap",
          "meaning": null
        },
        {
          "wrong": ["insiyatif"],
          "correct": "inisiyatif",
          "meaning": "öncelik, üstünlük"
        },
        {
          "wrong": ["istepne"],
          "correct": "stepne",
          "meaning": "yedek lastik"
        },
        {
          "wrong": ["istihap hatti"],
          "correct": "istiap haddi",
          "meaning": "içine alma sınırı, sığdırma sınırı"
        },
        {
          "wrong": ["izalasyon"],
          "correct": "izolasyon",
          "meaning": null
        }
      ]
    },
    {
      "letter": "K",
      "words": [
        {
          "wrong": ["karsör", "karisör"],
          "correct": "karoser",
          "meaning": null
        },
        {
          "wrong": ["kakafoni"],
          "correct": "kakofoni",
          "meaning": "ses uyumsuzluğu"
        },
        {
          "wrong": ["kalemşör"],
          "correct": "kalemşor",
          "meaning": "kalem savaşçısı"
        },
        {
          "wrong": ["kanpanya"],
          "correct": "kampanya",
          "meaning": null
        },
        {
          "wrong": ["kaporo"],
          "correct": "kaparo",
          "meaning": null
        },
        {
          "wrong": ["karegrafi", "kareografi"],
          "correct": "koreografi",
          "meaning": "figür ve anlatımların bütünü"
        },
        {
          "wrong": ["karekter"],
          "correct": "karakter",
          "meaning": null
        },
        {
          "wrong": ["karnıbahar"],
          "correct": "karnabahar",
          "meaning": null
        },
        {
          "wrong": ["kavonoz"],
          "correct": "kavanoz",
          "meaning": null
        },
        {
          "wrong": ["katalok"],
          "correct": "katalog",
          "meaning": null
        },
        {
          "wrong": ["kaysı"],
          "correct": "kayısı",
          "meaning": null
        },
        {
          "wrong": ["kırahatane"],
          "correct": "kıraathane",
          "meaning": null
        },
        {
          "wrong": ["kilot"],
          "correct": "külot",
          "meaning": null
        },
        {
          "wrong": ["kipri"],
          "correct": "kirpi",
          "meaning": null
        },
        {
          "wrong": ["kiprik"],
          "correct": "kirpik",
          "meaning": null
        },
        {
          "wrong": ["kitlemek"],
          "correct": "kilitlemek",
          "meaning": null
        },
        {
          "wrong": ["klavuz"],
          "correct": "kılavuz",
          "meaning": null
        },
        {
          "wrong": ["klüp"],
          "correct": "kulüp",
          "meaning": null
        },
        {
          "wrong": ["kokreç", "kokareç"],
          "correct": "kokoreç",
          "meaning": null
        },
        {
          "wrong": ["kolanya"],
          "correct": "kolonya",
          "meaning": null
        },
        {
          "wrong": ["kollej"],
          "correct": "kolej",
          "meaning": null
        },
        {
          "wrong": ["kolleksiyon"],
          "correct": "koleksiyon",
          "meaning": null
        },
        {
          "wrong": ["kollektif"],
          "correct": "kolektif",
          "meaning": null
        },
        {
          "wrong": ["komidin"],
          "correct": "komodin",
          "meaning": "küçük dolap"
        },
        {
          "wrong": ["kominist"],
          "correct": "komünist",
          "meaning": null
        },
        {
          "wrong": ["komünükasyon"],
          "correct": "komünikasyon",
          "meaning": "iletişim"
        },
        {
          "wrong": ["konsansüs"],
          "correct": "konsensüs",
          "meaning": "uzlaşma"
        },
        {
          "wrong": ["kontür", "kontur"],
          "correct": "kontör",
          "meaning": null
        },
        {
          "wrong": ["kopye"],
          "correct": "kopya",
          "meaning": null
        },
        {
          "wrong": ["kurdela", "kordale", "kurdale"],
          "correct": "kurdele",
          "meaning": null
        },
        {
          "wrong": ["küpür"],
          "correct": "kupür",
          "meaning": "giyside kesim"
        },
        {
          "wrong": ["küvöz"],
          "correct": "kuvöz",
          "meaning": "yaşanak"
        }
      ]
    },
    {
      "letter": "L",
      "words": [
        {
          "wrong": ["layik"],
          "correct": "laik",
          "meaning": null
        },
        {
          "wrong": ["labaratuar", "labaratuvar", "laboratuar"],
          "correct": "laboratuvar",
          "meaning": null
        },
        {
          "wrong": ["lağbo", "lavobo"],
          "correct": "lavabo",
          "meaning": null
        },
        {
          "wrong": ["laylon"],
          "correct": "naylon",
          "meaning": null
        }
      ]
    },
    {
      "letter": "M",
      "words": [
        {
          "wrong": ["nalet"],
          "correct": "lanet",
          "meaning": null
        },
        {
          "wrong": ["mahçup"],
          "correct": "mahcup",
          "meaning": null
        },
        {
          "wrong": ["mahfolmak"],
          "correct": "mahvolmak",
          "meaning": null
        },
        {
          "wrong": ["mahsuz", "masus"],
          "correct": "mahsus",
          "meaning": null
        },
        {
          "wrong": ["makina"],
          "correct": "makine",
          "meaning": null
        },
        {
          "wrong": ["maktül"],
          "correct": "maktul",
          "meaning": "öldürülmüş"
        },
        {
          "wrong": ["manüpülasyon"],
          "correct": "manipülasyon",
          "meaning": "yönlendirme, seçme"
        },
        {
          "wrong": ["matamatik"],
          "correct": "matematik",
          "meaning": null
        },
        {
          "wrong": ["mataryal"],
          "correct": "materyal",
          "meaning": null
        },
        {
          "wrong": ["maydonoz"],
          "correct": "maydanoz",
          "meaning": null
        },
        {
          "wrong": ["mefta"],
          "correct": "mevta",
          "meaning": "ölü, ölmüş kimse"
        },
        {
          "wrong": ["megoloman", "megolaman"],
          "correct": "megaloman",
          "meaning": "kendini çok büyük gören kimse"
        },
        {
          "wrong": ["melemen"],
          "correct": "menemen",
          "meaning": null
        },
        {
          "wrong": ["melhem"],
          "correct": "merhem",
          "meaning": null
        },
        {
          "wrong": ["menapoz"],
          "correct": "menopoz",
          "meaning": null
        },
        {
          "wrong": ["menejer", "menecer"],
          "correct": "menajer",
          "meaning": null
        },
        {
          "wrong": ["mentalite"],
          "correct": "mantalite",
          "meaning": "anlayış"
        },
        {
          "wrong": ["menüsküs"],
          "correct": "menisküs",
          "meaning": null
        },
        {
          "wrong": ["meyva"],
          "correct": "meyve",
          "meaning": null
        },
        {
          "wrong": ["miğde"],
          "correct": "mide",
          "meaning": null
        },
        {
          "wrong": ["mokasen"],
          "correct": "makosen",
          "meaning": "kısa ökçeli, bağsız ayakkabı"
        },
        {
          "wrong": ["motorsiklet"],
          "correct": "motosiklet",
          "meaning": null
        },
        {
          "wrong": ["mozayik"],
          "correct": "mozaik",
          "meaning": null
        },
        {
          "wrong": ["mönü"],
          "correct": "menü",
          "meaning": "yemek listesi"
        },
        {
          "wrong": ["muacir"],
          "correct": "muhacir",
          "meaning": null
        },
        {
          "wrong": ["muaffak"],
          "correct": "muvaffak",
          "meaning": null
        },
        {
          "wrong": ["muhattap"],
          "correct": "muhatap",
          "meaning": null
        },
        {
          "wrong": ["mundar"],
          "correct": "murdar",
          "meaning": "kirli, pis"
        },
        {
          "wrong": ["mustarip"],
          "correct": "muzdarip",
          "meaning": null
        },
        {
          "wrong": ["muşanba"],
          "correct": "muşamba",
          "meaning": null
        },
        {
          "wrong": ["muzur"],
          "correct": "muzır",
          "meaning": "zararlı"
        },
        {
          "wrong": ["münübüs"],
          "correct": "minibüs",
          "meaning": null
        },
        {
          "wrong": ["müracat"],
          "correct": "müracaat",
          "meaning": null
        },
        {
          "wrong": ["mürüvet", "mürivet"],
          "correct": "mürüvvet",
          "meaning": "cömertlik, yiğitlik"
        },
        {
          "wrong": ["müsayit"],
          "correct": "müsait",
          "meaning": null
        },
        {
          "wrong": ["müsbet"],
          "correct": "müspet",
          "meaning": null
        },
        {
          "wrong": ["müsvette"],
          "correct": "müsvedde",
          "meaning": null
        },
        {
          "wrong": ["mütaakip"],
          "correct": "müteakip",
          "meaning": null
        },
        {
          "wrong": ["mütahit"],
          "correct": "müteahhit",
          "meaning": null
        }
      ]
    },
    {
      "letter": "N",
      "words": [
        {
          "wrong": ["naturel"],
          "correct": "natürel",
          "meaning": "doğal"
        },
        {
          "wrong": ["nergiz"],
          "correct": "nergis",
          "meaning": null
        },
        {
          "wrong": ["nisbet"],
          "correct": "nispet",
          "meaning": null
        },
        {
          "wrong": ["nötür"],
          "correct": "nötr",
          "meaning": "etkisiz"
        }
      ]
    },
    {
      "letter": "O",
      "words": [
        {
          "wrong": ["oce"],
          "correct": "oje",
          "meaning": null
        },
        {
          "wrong": ["okşizen"],
          "correct": "oksijen",
          "meaning": null
        },
        {
          "wrong": ["oparasyon"],
          "correct": "operasyon",
          "meaning": null
        },
        {
          "wrong": ["opsayd"],
          "correct": "ofsayt",
          "meaning": null
        },
        {
          "wrong": ["orjinal"],
          "correct": "orijinal",
          "meaning": null
        },
        {
          "wrong": ["şok olmak"],
          "correct": "şoke olmak",
          "meaning": null
        }
      ]
    },
    {
      "letter": "Ö",
      "words": [
        {
          "wrong": ["öğe"],
          "correct": "öge",
          "meaning": null
        },
        {
          "wrong": ["ötenazi"],
          "correct": "ötanazi",
          "meaning": "ölme hakkı"
        }
      ]
    },
    {
      "letter": "P",
      "words": [
        {
          "wrong": ["palyanço", "palyoça"],
          "correct": "palyaço",
          "meaning": null
        },
        {
          "wrong": ["panaroma"],
          "correct": "panorama",
          "meaning": "genel görünüm"
        },
        {
          "wrong": ["pantalon"],
          "correct": "pantolon",
          "meaning": null
        },
        {
          "wrong": ["parağraf"],
          "correct": "paragraf",
          "meaning": null
        },
        {
          "wrong": ["pardesü"],
          "correct": "pardösü",
          "meaning": null
        },
        {
          "wrong": ["parelel"],
          "correct": "paralel",
          "meaning": null
        },
        {
          "wrong": ["parende"],
          "correct": "perende",
          "meaning": "havada dönerek atılan takla"
        },
        {
          "wrong": ["parlementer"],
          "correct": "parlamenter",
          "meaning": null
        },
        {
          "wrong": ["parlemento"],
          "correct": "parlamento",
          "meaning": null
        },
        {
          "wrong": ["payton"],
          "correct": "fayton",
          "meaning": null
        },
        {
          "wrong": ["penbe"],
          "correct": "pembe",
          "meaning": null
        },
        {
          "wrong": ["peştemal"],
          "correct": "peştamal",
          "meaning": null
        },
        {
          "wrong": ["pisiklet"],
          "correct": "bisiklet",
          "meaning": null
        },
        {
          "wrong": ["proğram", "prooram"],
          "correct": "program",
          "meaning": null
        },
        {
          "wrong": ["proleterya"],
          "correct": "proletarya",
          "meaning": "emekçi sınıfı"
        },
        {
          "wrong": ["promasyon"],
          "correct": "promosyon",
          "meaning": "özendirme"
        },
        {
          "wrong": ["provakatör"],
          "correct": "provokatör",
          "meaning": "kışkırtmacı"
        },
        {
          "wrong": ["psikiyatrist"],
          "correct": "psikiyatr",
          "meaning": null
        }
      ]
    },
    {
      "letter": "R",
      "words": [
        {
          "wrong": ["radyosyon"],
          "correct": "radyasyon",
          "meaning": null
        },
        {
          "wrong": ["rakkam"],
          "correct": "rakam",
          "meaning": null
        },
        {
          "wrong": ["raslantı"],
          "correct": "rastlantı",
          "meaning": null
        },
        {
          "wrong": ["rasgele"],
          "correct": "rastgele",
          "meaning": null
        },
        {
          "wrong": ["restoran"],
          "correct": "restoran",
          "meaning": null
        },
        {
          "wrong": ["revanş"],
          "correct": "rövanş",
          "meaning": null
        },
        {
          "wrong": ["rezarvasyon"],
          "correct": "rezervasyon",
          "meaning": null
        },
        {
          "wrong": ["riks"],
          "correct": "risk",
          "meaning": null
        },
        {
          "wrong": ["Roma rakamları"],
          "correct": "Romen rakamları",
          "meaning": null
        },
        {
          "wrong": ["ropörtaj"],
          "correct": "röportaj",
          "meaning": null
        }
      ]
    },
    {
      "letter": "S",
      "words": [
        {
          "wrong": ["sada"],
          "correct": "seda",
          "meaning": "ses"
        },
        {
          "wrong": ["safa"],
          "correct": "sefa",
          "meaning": "gönül rahatlığı"
        },
        {
          "wrong": ["sağnak"],
          "correct": "sağanak",
          "meaning": null
        },
        {
          "wrong": ["sandoviç", "sandöviç", "sandüviç"],
          "correct": "sandviç",
          "meaning": null
        },
        {
          "wrong": ["sarmısak"],
          "correct": "sarımsak",
          "meaning": null
        },
        {
          "wrong": ["satlık"],
          "correct": "satılık",
          "meaning": null
        },
        {
          "wrong": ["sellektör"],
          "correct": "selektör",
          "meaning": null
        },
        {
          "wrong": ["seramoni"],
          "correct": "seremoni",
          "meaning": "tören"
        },
        {
          "wrong": ["serbes"],
          "correct": "serbest",
          "meaning": null
        },
        {
          "wrong": ["seyehat"],
          "correct": "seyahat",
          "meaning": null
        },
        {
          "wrong": ["sezeryan"],
          "correct": "sezaryen",
          "meaning": null
        },
        {
          "wrong": ["silahşör"],
          "correct": "silahşor",
          "meaning": null
        },
        {
          "wrong": ["sohpet"],
          "correct": "sohbet",
          "meaning": null
        },
        {
          "wrong": ["soy kırımı"],
          "correct": "soykırım",
          "meaning": null
        },
        {
          "wrong": ["statyum"],
          "correct": "stadyum",
          "meaning": null
        },
        {
          "wrong": ["su basmanı"],
          "correct": "subasman",
          "meaning": "oturmalık"
        },
        {
          "wrong": ["subap", "supab", "sibop"],
          "correct": "supap",
          "meaning": null
        },
        {
          "wrong": ["sueter"],
          "correct": "süveter",
          "meaning": null
        },
        {
          "wrong": ["südyen", "sudyen"],
          "correct": "sütyen",
          "meaning": null
        },
        {
          "wrong": ["sükûtuhayal"],
          "correct": "sukutuhayal",
          "meaning": "hayal kırıklığı"
        },
        {
          "wrong": ["süpriz", "süprüz"],
          "correct": "sürpriz",
          "meaning": null
        },
        {
          "wrong": ["sütüdyo"],
          "correct": "stüdyo",
          "meaning": null
        }
      ]
    },
    {
      "letter": "Ş",
      "words": [
        {
          "wrong": ["şanzuman"],
          "correct": "şanzıman",
          "meaning": null
        },
        {
          "wrong": ["şarter"],
          "correct": "şalter",
          "meaning": null
        },
        {
          "wrong": ["şarz"],
          "correct": "şarj",
          "meaning": null
        },
        {
          "wrong": ["şayibe"],
          "correct": "şaibe",
          "meaning": null
        },
        {
          "wrong": ["şemşiye"],
          "correct": "şemsiye",
          "meaning": null
        },
        {
          "wrong": ["şevkat"],
          "correct": "şefkat",
          "meaning": null
        },
        {
          "wrong": ["şifai"],
          "correct": "şifahi",
          "meaning": null
        },
        {
          "wrong": ["şohben"],
          "correct": "şofben",
          "meaning": null
        },
        {
          "wrong": ["şöför"],
          "correct": "şoför",
          "meaning": null
        }
      ]
    },
    {
      "letter": "T",
      "words": [
        {
          "wrong": ["tabiyat"],
          "correct": "tabiat",
          "meaning": null
        },
        {
          "wrong": ["tahüt"],
          "correct": "taahhüt",
          "meaning": null
        },
        {
          "wrong": ["taamüden", "tamüden"],
          "correct": "taammüden",
          "meaning": "kasten, tasarlayarak"
        },
        {
          "wrong": ["tafsiye"],
          "correct": "tavsiye",
          "meaning": null
        },
        {
          "wrong": ["tahtarevalli"],
          "correct": "tahterevalli",
          "meaning": null
        },
        {
          "wrong": ["taktim"],
          "correct": "takdim",
          "meaning": null
        },
        {
          "wrong": ["taktir"],
          "correct": "takdir",
          "meaning": null
        },
        {
          "wrong": ["tanpon"],
          "correct": "tampon",
          "meaning": null
        },
        {
          "wrong": ["tastik"],
          "correct": "tasdik",
          "meaning": null
        },
        {
          "wrong": ["tasfir"],
          "correct": "tasvir",
          "meaning": null
        },
        {
          "wrong": ["tasviye"],
          "correct": "tasfiye",
          "meaning": "arıtma"
        },
        {
          "wrong": ["taşaron"],
          "correct": "taşeron",
          "meaning": "ikinci derecede müteahhit"
        },
        {
          "wrong": ["teferuat"],
          "correct": "teferruat",
          "meaning": null
        },
        {
          "wrong": ["tekneloji"],
          "correct": "teknoloji",
          "meaning": null
        },
        {
          "wrong": ["tekrardan"],
          "correct": "tekrar",
          "meaning": null
        },
        {
          "wrong": ["temize gitmek"],
          "correct": "temyize gitmek",
          "meaning": null
        },
        {
          "wrong": ["tenbel"],
          "correct": "tembel",
          "meaning": null
        },
        {
          "wrong": ["tenbih"],
          "correct": "tembih",
          "meaning": null
        },
        {
          "wrong": ["tenefüs"],
          "correct": "teneffüs",
          "meaning": null
        },
        {
          "wrong": ["teravi", "terevi"],
          "correct": "teravih",
          "meaning": null
        },
        {
          "wrong": ["tesbih"],
          "correct": "tespih",
          "meaning": null
        },
        {
          "wrong": ["tesbit"],
          "correct": "tespit",
          "meaning": null
        },
        {
          "wrong": ["teşfik"],
          "correct": "teşvik",
          "meaning": null
        },
        {
          "wrong": ["tetanoz"],
          "correct": "tetanos",
          "meaning": null
        },
        {
          "wrong": ["tiskinmek"],
          "correct": "tiksinmek",
          "meaning": null
        },
        {
          "wrong": ["tiyo"],
          "correct": "tüyo",
          "meaning": "gizli bilgi"
        },
        {
          "wrong": ["tolorans"],
          "correct": "tolerans",
          "meaning": null
        },
        {
          "wrong": ["tos"],
          "correct": "tost",
          "meaning": null
        },
        {
          "wrong": ["traş"],
          "correct": "tıraş",
          "meaning": null
        },
        {
          "wrong": ["tribuşon", "tirbüşon"],
          "correct": "tirbuşon",
          "meaning": "burgu"
        },
        {
          "wrong": ["türübün"],
          "correct": "tribün",
          "meaning": null
        }
      ]
    },
    {
      "letter": "U",
      "words": [
        {
          "wrong": ["ukte"],
          "correct": "ukde",
          "meaning": "yükümlülük, sorumluluk"
        },
        {
          "wrong": ["ultrasyon"],
          "correct": "ultrason",
          "meaning": "yansılanım"
        },
        {
          "wrong": ["ultümaton", "ültimatom"],
          "correct": "ültimatom",
          "meaning": "bir devletin başka bir devlete verdiği nota"
        },
        {
          "wrong": ["usûl"],
          "correct": "usul",
          "meaning": null
        },
        {
          "wrong": ["utopya"],
          "correct": "ütopya",
          "meaning": null
        }
      ]
    },
    {
      "letter": "Ü",
      "words": [
        {
          "wrong": ["ünüforma"],
          "correct": "üniforma",
          "meaning": null
        },
        {
          "wrong": ["ünvan"],
          "correct": "unvan",
          "meaning": null
        },
        {
          "wrong": ["üvertür"],
          "correct": "uvertür",
          "meaning": "konser öncesi çalınan parça"
        }
      ]
    },
    {
      "letter": "V",
      "words": [
        {
          "wrong": ["valeybol", "veleybol"],
          "correct": "voleybol",
          "meaning": null
        },
        {
          "wrong": ["vehamet"],
          "correct": "vahamet",
          "meaning": "güçlük, tehlikeli durum"
        },
        {
          "wrong": ["vejeteryan"],
          "correct": "vejetaryen",
          "meaning": "etyemez"
        },
        {
          "wrong": ["vürüs"],
          "correct": "virüs",
          "meaning": "parazit"
        }
      ]
    },
    {
      "letter": "Y",
      "words": [
        {
          "wrong": ["yalnış"],
          "correct": "yanlış",
          "meaning": null
        },
        {
          "wrong": ["yayınlamak"],
          "correct": "yayımlamak",
          "meaning": null
        },
        {
          "wrong": ["yımırta"],
          "correct": "yumurta",
          "meaning": null
        },
        {
          "wrong": ["yövmiye"],
          "correct": "yevmiye",
          "meaning": null
        }
      ]
    },
    {
      "letter": "Z",
      "words": [
        {
          "wrong": ["zenaat"],
          "correct": "zanaat",
          "meaning": null
        },
        {
          "wrong": ["zerafet"],
          "correct": "zarafet",
          "meaning": "zariflik"
        },
        {
          "wrong": ["zınba"],
          "correct": "zımba",
          "meaning": null
        }
      ]
    }
  ],
  "metadata": {
    "source": "İBB Yavuz Sultan Selim Kız AİHL / Türk Dili ve Edebiyatı",
    "totalWords": 222,
    "version": "1.0",
    "lastUpdated": "2026-02-21"
  }
}

